altmorph/__init__.py
altmorph/data/lemma-multi/nno.csv
altmorph/data/lemma-multi/nob.csv
altmorph-0.1.0.dist-info/licenses/LICENSE
altmorph-0.1.0.dist-info/METADATA
altmorph-0.1.0.dist-info/WHEEL
altmorph-0.1.0.dist-info/entry_points.txt
altmorph-0.1.0.dist-info/top_level.txt
altmorph-0.1.0.dist-info/RECORD
