Metadata-Version: 2.4
Name: altmorph
Version: 0.1.0
Summary: Context-aware Norwegian morphological alternative generator
Home-page: https://github.com/yourusername/altmorph
Author: Pere
Author-email: Pere <your.email@example.com>
License:                                  Apache License
Project-URL: Homepage, https://github.com/yourusername/altmorph
Project-URL: Bug Reports, https://github.com/yourusername/altmorph/issues
Project-URL: Source, https://github.com/yourusername/altmorph
Keywords: morphology,norwegian,nlp,linguistics,alternatives,ordbank,pos,bert
Classifier: Development Status :: 4 - Beta
Classifier: Intended Audience :: Science/Research
Classifier: Topic :: Text Processing :: Linguistic
Classifier: Topic :: Scientific/Engineering :: Artificial Intelligence
Classifier: License :: OSI Approved :: Apache Software License
Classifier: Programming Language :: Python :: 3
Classifier: Programming Language :: Python :: 3.8
Classifier: Programming Language :: Python :: 3.9
Classifier: Programming Language :: Python :: 3.10
Classifier: Programming Language :: Python :: 3.11
Classifier: Operating System :: OS Independent
Requires-Python: >=3.8
License-File: LICENSE
Requires-Dist: datasets>=3.1.0
Requires-Dist: hf-transfer>=0.1.9
Requires-Dist: requests>=2.25.1
Requires-Dist: torch>=1.9.0
Requires-Dist: transformers>=4.20.0
Dynamic: author
Dynamic: home-page
Dynamic: license-file
Dynamic: requires-python
